CHANGES.txt
CONTRIBUTORS.txt
README.txt
bootstrap.py
buildout.cfg
setup.py
collective/__init__.py
collective.buildbot.egg-info/PKG-INFO
collective.buildbot.egg-info/SOURCES.txt
collective.buildbot.egg-info/dependency_links.txt
collective.buildbot.egg-info/entry_points.txt
collective.buildbot.egg-info/namespace_packages.txt
collective.buildbot.egg-info/not-zip-safe
collective.buildbot.egg-info/requires.txt
collective.buildbot.egg-info/top_level.txt
collective/buildbot/README.txt
collective/buildbot/__init__.py
collective/buildbot/buildbot.bat
collective/buildbot/buildbot.tac_tmpl
collective/buildbot/buildbot_service.py
collective/buildbot/master.py
collective/buildbot/master_recipe.py
collective/buildbot/overrides.py
collective/buildbot/poller.py
collective/buildbot/poller_recipe.py
collective/buildbot/project.py
collective/buildbot/project_recipe.py
collective/buildbot/recipe.py
collective/buildbot/scheduler.py
collective/buildbot/scripts.py
collective/buildbot/slave.tac_tmpl
collective/buildbot/slave_recipe.py
collective/buildbot/utils.py
collective/buildbot/docs/fullexample.txt
collective/buildbot/docs/master.txt
collective/buildbot/docs/poller.txt
collective/buildbot/docs/project.txt
collective/buildbot/docs/sample.cfg
collective/buildbot/docs/slave.txt
collective/buildbot/docs/svnauth.txt
collective/buildbot/templates/__init__.py
collective/buildbot/templates/buildbot/bootstrap.py
collective/buildbot/templates/buildbot/buildout.cfg_tmpl
collective/buildbot/templates/buildbot/master.cfg_tmpl
collective/buildbot/templates/buildbot/slave.cfg_tmpl
collective/buildbot/templates/buildbot/public_html/buildbot.css
collective/buildbot/tests/__init__.py
collective/buildbot/tests/test_docs.py
collective/buildbot/tests/test_scheduler.py