Metadata-Version: 1.0
Name: collective.buildbot
Version: 0.4.1
Summary: A set of zc.buildout recipes and support for declarative configuration for Buildbot
Home-page: http://pypi.python.org/pypi/collective.buildbot
Author: Gael Pasgrimaud
Author-email: gael.pasgrimaud@ingeniweb.com
License: ZPL
Keywords: buildout buildbot
Platform: UNKNOWN
Classifier: Framework :: Buildout
Classifier: Intended Audience :: Developers
Classifier: Topic :: Software Development :: Build Tools
Classifier: Topic :: Software Development :: Libraries :: Python Modules
Classifier: License :: OSI Approved :: Zope Public License
